{
    "emoji": "\ud83c\udd99",
    "code": "U+1F199",
    "short_name": "UP! button",
    "keywords": [
        "progress",
        "advancement",
        "ascension",
        "motivation"
    ],
    "interpretation": "The UP! button signifies a call to action, urging you to take the next step towards progress. This card is a symbol of motivation and a reminder that you have the power to move forward and achieve your goals. It represents an upward journey, indicating that you are on the path towards advancement and ascension. This card serves as a catalyst for growth and encourages you to stay focused on your objectives.\n\nThe UP! button is a powerful reminder that success is within reach, and you are capable of reaching new heights. It signifies a shift in energy and a turning point in your life, urging you to embrace change and move towards a brighter future. This card encourages you to have faith in your abilities and trust the universe to guide you towards your destiny.\n\nWhen the UP! button appears in a reading, it is a sign that you are making progress and moving in the right direction. It is a call to action, urging you to take the next step towards your goals. This card signifies the beginning of a new journey, one that is filled with promise and potential. It is a reminder that you are capable of achieving greatness and encourages you to stay focused on your path."
}