{
    "emoji": "\ud83c\uddec\ud83c\uddea",
    "code": "U+1F1EC U+1F1EA",
    "short_name": "flag: Georgia",
    "keywords": [
        "national pride",
        "cultural heritage",
        "independence",
        "ancestry",
        "moral values",
        "identity"
    ],
    "interpretation": "The \"flag: Georgia\" card represents a sense of national pride and cultural heritage. It symbolizes independence and the desire to preserve one's own identity. This card may indicate a need to reconnect with one's roots and to honor one's ancestry. It can also suggest a desire to assert one's independence and to stand up for one's beliefs. The flag of Georgia is characterized by its distinctive red cross on a white background, which may represent purity and righteousness. This card may suggest a need to uphold one's moral values and to strive for a higher purpose. Overall, the \"flag: Georgia\" card invites us to embrace our cultural identity and to be proud of who we are. It reminds us to honor our past while staying true to our own path in life."
}