{
    "emoji": "\ud83c\udf82",
    "code": "U+1F382",
    "short_name": "birthday cake",
    "keywords": [
        "celebration",
        "indulgence",
        "sweetness",
        "wishes",
        "joy"
    ],
    "interpretation": "The Birthday Cake card represents a time of celebration and indulgence. It signifies a moment of sweetness in your life, where you can enjoy the fruits of your labor and take a break from your worries. This card also speaks to the idea of wishes and manifestation, as blowing out the candles and making a wish is a time-honored tradition. It encourages you to tap into your joy and revel in the happiness that surrounds you. This card also suggests that you should take time to appreciate the good things in your life and recognize the people who make them possible. Overall, the Birthday Cake card is a reminder to celebrate and savor the moments of happiness that come your way."
}