{
    "emoji": "\ud83c\udf89",
    "code": "U+1F389",
    "short_name": "party popper",
    "keywords": [
        "celebration",
        "joy",
        "excitement",
        "new beginnings",
        "responsibility"
    ],
    "interpretation": "The Party Popper emoji is a symbol of celebration and excitement. It represents the thrill of an event or occasion, and the joy that comes with it. This card may indicate a time of happiness and merriment, where you are surrounded by friends and loved ones. It can also suggest that you are feeling festive and ready to let loose.\n\nThe Party Popper can also represent a new beginning or milestone in your life. Perhaps you are starting a new job, moving to a new city, or embarking on a new adventure. This card signifies that you are ready to embrace this change with open arms and celebrate the journey ahead.\n\nOn the other hand, this card can also warn against excessive partying or reckless behavior. It is important to remember to celebrate responsibly and not get carried away with the excitement of the moment. Be mindful of your actions and take care of yourself and those around you.\n\nOverall, the Party Popper emoji is a symbol of joy and celebration, reminding you to enjoy the good times and make the most of life's special moments."
}