{
    "emoji": "\ud83d\udc17",
    "code": "U+1F417",
    "short_name": "boar",
    "keywords": [
        "strength",
        "courage",
        "ferocity",
        "determination",
        "resilience",
        "overcoming obstacles",
        "success",
        "aggression",
        "conflict",
        "grounded",
        "focus",
        "goals",
        "wisdom",
        "fertility",
        "abundance",
        "growth",
        "prosperity"
    ],
    "interpretation": "The boar emoji represents strength, courage, and ferocity. This card is a reminder to tap into your inner power and face challenges head-on. The boar's fierce determination and resilience make it a symbol of overcoming obstacles and achieving success. However, be mindful not to let your aggression get the best of you, as this can lead to reckless behavior and conflict. Stay grounded and focused on your goals, and use your strength wisely to achieve what you desire. The boar also represents fertility and abundance, suggesting that your efforts will be rewarded with growth and prosperity. Overall, this card is a call to action to embrace your inner strength and fearlessly pursue your ambitions."
}