{
    "emoji": "\ud83c\uddf2\ud83c\uddf7",
    "code": "U+1F1F2 U+1F1F7",
    "short_name": "flag: Mauritania",
    "keywords": [
        "pride",
        "independence",
        "cultural diversity"
    ],
    "interpretation": "The Mauritania flag is a symbol of national pride and independence. The green represents the country's agriculture and hope for a bright future, while the gold represents the desert and the country's mineral wealth. The crescent and star are symbols of Islam, which is the dominant religion in Mauritania. \n\nIn a tarot reading, this card can represent a strong sense of cultural identity and pride. It may indicate a need to embrace your heritage and celebrate the diversity that makes you unique. This card can also suggest a desire for independence and a need to break free from any oppressive or limiting situations. \n\nThe Mauritania flag encourages you to stand tall and be proud of who you are. Embrace your unique qualities and use them to your advantage. This card also reminds you to be mindful of the importance of your roots and to honor the traditions and customs of your ancestors."
}