{
    "emoji": "\ud83d\udc69\u200d\ud83d\ude80",
    "code": "U+1F469 U+200D U+1F680",
    "short_name": "woman astronaut",
    "keywords": [
        "exploration",
        "bravery",
        "adventure",
        "progression",
        "independence"
    ],
    "interpretation": "The woman astronaut card represents a fearless and adventurous spirit, unafraid to explore the unknown and push boundaries. This card signifies a drive to seek out new experiences and challenges, and to pursue them with a sense of purpose and determination. The woman astronaut symbolizes a pioneering spirit, unafraid to take risks and forge her own path in life. She embodies a strong sense of independence, self-sufficiency, and self-reliance. \n\nThis card can also represent a desire for progress and innovation, an urge to advance and improve oneself and the world around them. The woman astronaut inspires us to look beyond our current limitations and reach for the stars. She reminds us that anything is possible if we have the courage to believe in ourselves and take bold action.\n\nOverall, the woman astronaut card encourages us to embrace our adventurous spirit, to be brave in the face of challenges, and to always strive for progress and growth."
}