{
    "emoji": "\ud83d\uded5",
    "code": "U+1F6D5",
    "short_name": "hindu temple",
    "keywords": [
        "spirituality",
        "devotion",
        "community",
        "faith",
        "tradition",
        "worship",
        "pilgrimage",
        "enlightenment"
    ],
    "interpretation": "The Hindu Temple emoji represents spirituality, devotion, and a sense of community. It can symbolize a need for inner peace and reflection, and a desire to connect with a higher power. This card may suggest a need for a spiritual practice or guidance, or the presence of a spiritual leader or mentor in your life. It can also indicate a sense of belonging to a community or group that shares your beliefs and values. Keywords associated with this card include faith, tradition, worship, pilgrimage, and enlightenment. When this card appears in a reading, it may suggest a need to deepen your spiritual connection or seek guidance from a trusted source. It can also indicate a positive outcome in matters of faith, religion, or cultural traditions. Embrace the energy of the Hindu Temple and trust in the power of the divine to guide you on your path."
}