{
    "emoji": "\ud83e\udd64",
    "code": "U+1F964",
    "short_name": "cup with straw",
    "keywords": [
        "refreshment",
        "satisfaction",
        "indulgence",
        "thirst",
        "pleasure",
        "celebration",
        "relaxation",
        "self-care",
        "balance"
    ],
    "interpretation": "The Cup with Straw emoji represents refreshment, satisfaction, and indulgence. It suggests that the querent may be feeling thirsty for something in their life, whether it be emotional, physical, or spiritual. This card encourages the querent to take a break, enjoy a drink, and replenish their energy. The Cup with Straw also indicates a desire for pleasure and a need to treat oneself. It may signify a time of celebration, relaxation, or self-care. However, the Cup with Straw warns against overindulgence and urges the querent to maintain a balance between enjoyment and responsibility. Overall, this card is a reminder to take care of oneself and find joy in the simple things in life."
}