{
    "emoji": "\ud83e\udd98",
    "code": "U+1F998",
    "short_name": "kangaroo",
    "keywords": [
        "strength",
        "agility",
        "adaptability",
        "exploration",
        "risk-taking",
        "balance",
        "stability"
    ],
    "interpretation": "The kangaroo emoji represents strength and agility, symbolizing the ability to jump over obstacles and make quick movements. It suggests a need to be adaptable and flexible in difficult situations, as well as a desire to explore and take risks. The kangaroo can also indicate a need for balance, as it often stands on its hind legs while using its tail for support. This may suggest a need to find stability in one's life and maintain a strong foundation. Keywords associated with this card include: strength, agility, adaptability, exploration, risk-taking, balance, stability."
}